[
  {
    "BTCPERP@perpetual@bitget": {
      "funding": 0.0001
    },
    "timestamp": "2024-05-28 15:21:27",
    "_doc": "6a146131-6a90-46a2-89b6-4786862347d4"
  },
  {
    "BTCPERP@perpetual@bitget": {
      "funding": 0.0001
    },
    "timestamp": "2024-05-28 15:21:25",
    "_doc": "92789f9a-aaab-4a2d-91a6-856e8f252a1f"
  },
  {
    "BTCUSD@perpetual@bitget": {
      "funding": 0.000115
    },
    "timestamp": "2024-05-28 15:21:24",
    "_doc": "82eae305-daec-4742-9945-a80060071b93"
  },
  {
    "BTCUSD@perpetual@bitget": {
      "funding": 0.000115
    },
    "timestamp": "2024-05-28 15:21:23",
    "_doc": "d2c424b5-7606-48b9-ad0b-9556a92c572e"
  },
  {
    "BTCUSDT@perpetual@bitget": {
      "funding": 0.000119
    },
    "timestamp": "2024-05-28 15:21:23",
    "_doc": "856e680b-bfd2-43b5-a1d9-91c020ca6a49"
  },
  {
    "BTCUSDT@perpetual@bitget": {
      "funding": 0.000119
    },
    "timestamp": "2024-05-28 15:21:22",
    "_doc": "28ed24ac-0d64-437b-a1e2-8273b03c2278"
  },
  {
    "BTCUSD@perpetual@bitget": {
      "funding": 0.000115
    },
    "timestamp": "2024-05-28 15:21:22",
    "_doc": "5486ed51-a767-44ab-9b25-6ebed5fc757e"
  },
  {
    "BTCPERP@perpetual@bitget": {
      "funding": 0.0001
    },
    "timestamp": "2024-05-28 15:21:21",
    "_doc": "c5724aab-3fad-4bb7-839d-66b71d67d576"
  },
  {
    "BTCPERP@perpetual@bitget": {
      "funding": 0.0001
    },
    "timestamp": "2024-05-28 15:21:20",
    "_doc": "9e67cc21-2fd6-4094-9b4c-a3a1324cba85"
  },
  {
    "BTCUSD@perpetual@bitget": {
      "funding": 0.000115
    },
    "timestamp": "2024-05-28 15:21:18",
    "_doc": "9a08ec1e-f1ad-4d20-becc-0ca0fa640dd0"
  },
  {
    "BTCUSDT@perpetual@bitget": {
      "funding": 0.000119
    },
    "timestamp": "2024-05-28 15:21:17",
    "_doc": "68e20636-4c61-4a00-a4ca-7c03d622d207"
  },
  {
    "BTCUSDT@perpetual@bitget": {
      "funding": 0.000119
    },
    "timestamp": "2024-05-28 15:21:17",
    "_doc": "fc22c61d-b786-40ba-a8b2-061d92fe98a3"
  },
  {
    "BTCPERP@perpetual@bitget": {
      "funding": 0.0001
    },
    "timestamp": "2024-05-28 15:21:16",
    "_doc": "432b11ae-a0c7-4da8-9895-bde88c856898"
  },
  {
    "BTCUSD@perpetual@bitget": {
      "funding": 0.000115
    },
    "timestamp": "2024-05-28 15:21:16",
    "_doc": "b7b70b4d-d7c0-4f1f-8e9a-0dcf47a8830e"
  },
  {
    "BTCPERP@perpetual@bitget": {
      "funding": 0.0001
    },
    "timestamp": "2024-05-28 15:21:16",
    "_doc": "200f1329-4d29-462f-9220-6bcbf1bb8174"
  },
  {
    "BTCUSDT@perpetual@bitget": {
      "funding": 0.000119
    },
    "timestamp": "2024-05-28 15:21:13",
    "_doc": "9411398f-ae1f-4c30-ab47-94c0326ebdbd"
  },
  {
    "BTCPERP@perpetual@bitget": {
      "funding": 0.0001
    },
    "timestamp": "2024-05-28 14:25:09",
    "_doc": "41410408-9d8e-4472-96ce-2f6432eb66d1"
  },
  {
    "BTCUSD@perpetual@bitget": {
      "funding": 0.000115
    },
    "timestamp": "2024-05-28 14:25:09",
    "_doc": "e829647e-8c0b-443f-931c-371cf12d7bff"
  },
  {
    "BTCUSDT@perpetual@bitget": {
      "funding": 0.000119
    },
    "timestamp": "2024-05-28 14:25:09",
    "_doc": "e63c8551-7ed6-468c-a8be-1148a8469bf7"
  },
  {
    "BTCUSD@perpetual@bitget": {
      "funding": 0.000115
    },
    "timestamp": "2024-05-28 14:24:53",
    "_doc": "fcf0c87b-1e55-46b0-8e07-54866753b9b7"
  },
  {
    "BTCPERP@perpetual@bitget": {
      "funding": 0.0001
    },
    "timestamp": "2024-05-28 14:24:53",
    "_doc": "57fa4c16-c8f2-4b47-8c8c-90ccca4c8c12"
  },
  {
    "BTCUSDT@perpetual@bitget": {
      "funding": 0.000119
    },
    "timestamp": "2024-05-28 14:24:53",
    "_doc": "ec48569a-434e-45a7-a1ec-38fde443c035"
  },
  {
    "BTCUSDT@perpetual@bitget": {
      "funding": 0.000119
    },
    "timestamp": "2024-05-28 14:17:46",
    "_doc": "10849bf8-2966-4f8b-ac8f-719c053cd77a"
  },
  {
    "BTCPERP@perpetual@bitget": {
      "funding": 0.0001
    },
    "timestamp": "2024-05-28 14:17:46",
    "_doc": "80de3469-9cba-449f-841e-9dd5969741f8"
  },
  {
    "BTCUSD@perpetual@bitget": {
      "funding": 0.000115
    },
    "timestamp": "2024-05-28 14:17:46",
    "_doc": "7cccdda5-4092-44b3-ad30-d04717001af7"
  },
  {
    "BTCPERP@perpetual@bitget": {
      "funding": 0.0001
    },
    "timestamp": "2024-05-28 14:17:31",
    "_doc": "dab6b2b8-960a-4b7b-92c2-56c6a693d92a"
  },
  {
    "BTCUSDT@perpetual@bitget": {
      "funding": 0.000119
    },
    "timestamp": "2024-05-28 14:17:31",
    "_doc": "5bd96ff9-f9b4-47b1-8927-040683f017db"
  },
  {
    "BTCUSD@perpetual@bitget": {
      "funding": 0.000115
    },
    "timestamp": "2024-05-28 14:17:31",
    "_doc": "19817656-ae62-493e-ba74-3c4c5164b4b4"
  }
]