[
    {
        "BTC_USDT": [
            {
                "r": "0.0001",
                "t": 1712131200
            }
        ],
        "BTC_USD": [
            {
                "r": "0.0001",
                "t": 1712131200
            }
        ],
        "_doc": "e495661f-8ad9-4b87-a4c8-6df268a08143"
    },
    {
        "BTC_USDT": [
            {
                "r": "0.0001",
                "t": 1712131200
            }
        ],
        "BTC_USD": [
            {
                "r": "0.0001",
                "t": 1712131200
            }
        ],
        "_doc": "47cbdf54-c260-4b8b-a36a-284f3a8eadd1"
    }
]