[
  {
    "data": [
      {
        "longAccount": "0.7377",
        "longShortRatio": "2.8124",
        "shortAccount": "0.2623",
        "pair": "BTCUSD",
        "timestamp": 1717966800000
      }
    ],
    "objective": "gta",
    "_doc": "87db7531-4238-40fe-bd46-e4cb451b2524"
  },
  {
    "data": [
      {
        "symbol": "BTCDOMUSDT",
        "longAccount": "0.5446",
        "longShortRatio": "1.1961",
        "shortAccount": "0.4554",
        "timestamp": 1717966800000
      }
    ],
    "objective": "ttp",
    "_doc": "bc448c87-8c8b-47a0-b163-834990898f7a"
  },
  {
    "data": [
      {
        "symbol": "BTCUSDC",
        "longAccount": "0.5570",
        "longShortRatio": "1.2573",
        "shortAccount": "0.4430",
        "timestamp": 1717967100000
      }
    ],
    "objective": "tta",
    "_doc": "acdf730d-12ca-4999-91e3-73013e86148e"
  },
  {
    "data": [
      {
        "symbol": "BTCUSDT_240628",
        "longAccount": "0.6907",
        "longShortRatio": "2.2333",
        "shortAccount": "0.3093",
        "timestamp": 1717967100000
      }
    ],
    "objective": "ttp",
    "_doc": "5796278d-974e-45ad-8f17-1419418a6c29"
  },
  {
    "data": [
      {
        "symbol": "BTCUSDT_240927",
        "longAccount": "0.5729",
        "longShortRatio": "1.3414",
        "shortAccount": "0.4271",
        "timestamp": 1717967100000
      }
    ],
    "objective": "tta",
    "_doc": "d77aea70-0edc-47fc-a053-ef9cb69d68ee"
  },
  {
    "data": [
      {
        "symbol": "BTCUSDT_240628",
        "longAccount": "0.5666",
        "longShortRatio": "1.3073",
        "shortAccount": "0.4334",
        "timestamp": 1717966800000
      }
    ],
    "objective": "tta",
    "_doc": "f4900d14-5ef6-45b2-ac55-792733ce547f"
  },
  {
    "data": [],
    "objective": "tta",
    "_doc": "f14f65b2-6e75-46a3-a0e9-e82dc6bad56b"
  },
  {
    "data": [
      {
        "symbol": "BTCUSDT",
        "longAccount": "0.6035",
        "longShortRatio": "1.5221",
        "shortAccount": "0.3965",
        "timestamp": 1717966800000
      }
    ],
    "objective": "tta",
    "_doc": "f8952a7a-49bf-47c2-a66f-f829ed3b9325"
  },
  {
    "data": [
      {
        "symbol": "BTCUSDT_240927",
        "longAccount": "0.7439",
        "longShortRatio": "2.9044",
        "shortAccount": "0.2561",
        "timestamp": 1717967100000
      }
    ],
    "objective": "ttp",
    "_doc": "3981b86c-38c0-4e3e-9512-75e6681614bf"
  },
  {
    "data": [
      {
        "symbol": "BTCDOMUSDT",
        "longAccount": "0.5918",
        "longShortRatio": "1.4498",
        "shortAccount": "0.4082",
        "timestamp": 1717967100000
      }
    ],
    "objective": "gta",
    "_doc": "6eb7aede-8da6-4528-8947-df1149e5b30f"
  },
  {
    "data": [],
    "objective": "ttp",
    "_doc": "8c5c3479-a710-4ab9-a6a6-37a7dabe557d"
  },
  {
    "data": [
      {
        "symbol": "BTCUSDT_240927",
        "longAccount": "0.5397",
        "longShortRatio": "1.1725",
        "shortAccount": "0.4603",
        "timestamp": 1717967100000
      }
    ],
    "objective": "gta",
    "_doc": "1a56e166-78a2-47f9-ba98-2a2d158bcf30"
  },
  {
    "data": [
      {
        "shortPosition": "0.4393",
        "longShortRatio": "1.2761",
        "longPosition": "0.5607",
        "pair": "BTCUSD",
        "timestamp": 1717967100000
      }
    ],
    "objective": "ttp",
    "_doc": "6ea15503-5c4a-4c6e-a01e-c4b10d802894"
  },
  {
    "data": [
      {
        "symbol": "BTCDOMUSDT",
        "longAccount": "0.5938",
        "longShortRatio": "1.4615",
        "shortAccount": "0.4063",
        "timestamp": 1717967100000
      }
    ],
    "objective": "tta",
    "_doc": "b014ac69-41a6-46cb-bab0-246f3e70b4e4"
  },
  {
    "data": [
      {
        "longAccount": "0.7377",
        "longShortRatio": "2.8124",
        "shortAccount": "0.2623",
        "pair": "BTCUSD",
        "timestamp": 1717966800000
      }
    ],
    "objective": "tta",
    "_doc": "5c1301c6-26b0-498a-a506-3e16f4ad1489"
  },
  {
    "data": [],
    "objective": "gta",
    "_doc": "e6e59fd8-bf89-471b-b682-a773ee6dbdf6"
  },
  {
    "data": [
      {
        "symbol": "BTCUSDC",
        "longAccount": "0.5538",
        "longShortRatio": "1.2411",
        "shortAccount": "0.4462",
        "timestamp": 1717967100000
      }
    ],
    "objective": "gta",
    "_doc": "bc50ea17-60bc-46a0-8717-8ad07eb450e1"
  },
  {
    "data": [
      {
        "symbol": "BTCUSDT",
        "longAccount": "0.5972",
        "longShortRatio": "1.4826",
        "shortAccount": "0.4028",
        "timestamp": 1717966800000
      }
    ],
    "objective": "gta",
    "_doc": "2388a3e3-1c1e-4e61-abf0-e27ec15ea301"
  },
  {
    "data": [
      {
        "symbol": "BTCUSDT_240628",
        "longAccount": "0.5469",
        "longShortRatio": "1.2070",
        "shortAccount": "0.4531",
        "timestamp": 1717966800000
      }
    ],
    "objective": "gta",
    "_doc": "26538c8c-4bc2-4595-8128-943dfbaa45db"
  },
  {
    "data": [
      {
        "symbol": "BTCUSDC",
        "longAccount": "0.5651",
        "longShortRatio": "1.2995",
        "shortAccount": "0.4349",
        "timestamp": 1717966800000
      }
    ],
    "objective": "ttp",
    "_doc": "41129144-09b7-4064-98f3-8226984daf1d"
  },
  {
    "data": [
      {
        "symbol": "BTCUSDT",
        "longAccount": "0.5831",
        "longShortRatio": "1.3985",
        "shortAccount": "0.4169",
        "timestamp": 1717966800000
      }
    ],
    "objective": "ttp",
    "_doc": "9e59eee5-8b59-40be-a1ce-fe00bd83b7a3"
  },
  {
    "data": [],
    "objective": "ttp",
    "_doc": "0b4a1088-7f2e-4802-a424-f2f52bd1dc8c"
  },
  {
    "data": [
      {
        "symbol": "BTCUSDC",
        "longAccount": "0.5651",
        "longShortRatio": "1.2995",
        "shortAccount": "0.4349",
        "timestamp": 1717966800000
      }
    ],
    "objective": "ttp",
    "_doc": "c38eb2d2-65cc-457a-bc94-bbb9448eaf1a"
  },
  {
    "data": [],
    "objective": "gta",
    "_doc": "9d7e117b-ea78-4370-a054-61be52a2e8e7"
  },
  {
    "data": [
      {
        "symbol": "BTCUSDT",
        "longAccount": "0.5831",
        "longShortRatio": "1.3985",
        "shortAccount": "0.4169",
        "timestamp": 1717966800000
      }
    ],
    "objective": "ttp",
    "_doc": "44f8ed61-6799-4b94-bab0-66b649b503ef"
  },
  {
    "data": [
      {
        "symbol": "BTCUSDT",
        "longAccount": "0.5972",
        "longShortRatio": "1.4826",
        "shortAccount": "0.4028",
        "timestamp": 1717966800000
      }
    ],
    "objective": "gta",
    "_doc": "3963c5dd-1dc8-493e-ad4f-8e1ea95a0695"
  },
  {
    "data": [
      {
        "symbol": "BTCDOMUSDT",
        "longAccount": "0.5446",
        "longShortRatio": "1.1961",
        "shortAccount": "0.4554",
        "timestamp": 1717966800000
      }
    ],
    "objective": "ttp",
    "_doc": "38f40a9c-26eb-4bba-ada3-a683e94a3af0"
  },
  {
    "data": [
      {
        "shortPosition": "0.4393",
        "longShortRatio": "1.2761",
        "longPosition": "0.5607",
        "pair": "BTCUSD",
        "timestamp": 1717967100000
      }
    ],
    "objective": "ttp",
    "_doc": "7ef7f841-5575-4685-b64d-5f97df01dc2b"
  },
  {
    "data": [
      {
        "longAccount": "0.7377",
        "longShortRatio": "2.8124",
        "shortAccount": "0.2623",
        "pair": "BTCUSD",
        "timestamp": 1717966800000
      }
    ],
    "objective": "gta",
    "_doc": "489631df-f4db-4fe5-b601-30f842324f57"
  },
  {
    "data": [
      {
        "symbol": "BTCUSDT_240927",
        "longAccount": "0.7439",
        "longShortRatio": "2.9044",
        "shortAccount": "0.2561",
        "timestamp": 1717967100000
      }
    ],
    "objective": "ttp",
    "_doc": "ffd7766c-938a-4a9e-b571-5a6f68a72ad1"
  },
  {
    "data": [
      {
        "symbol": "BTCUSDT_240628",
        "longAccount": "0.5469",
        "longShortRatio": "1.2070",
        "shortAccount": "0.4531",
        "timestamp": 1717966800000
      }
    ],
    "objective": "gta",
    "_doc": "9a59781a-3d19-4c34-8d02-5a68dc4c50dd"
  },
  {
    "data": [
      {
        "symbol": "BTCUSDT",
        "longAccount": "0.6035",
        "longShortRatio": "1.5221",
        "shortAccount": "0.3965",
        "timestamp": 1717966800000
      }
    ],
    "objective": "tta",
    "_doc": "fc5afc7e-cedd-4d51-b299-fd5c16a48426"
  },
  {
    "data": [
      {
        "symbol": "BTCUSDT_240927",
        "longAccount": "0.5729",
        "longShortRatio": "1.3414",
        "shortAccount": "0.4271",
        "timestamp": 1717966800000
      }
    ],
    "objective": "tta",
    "_doc": "51ed96ed-3caf-4666-8914-ebe4db906fe6"
  },
  {
    "data": [
      {
        "symbol": "BTCUSDT_240628",
        "longAccount": "0.6907",
        "longShortRatio": "2.2329",
        "shortAccount": "0.3093",
        "timestamp": 1717966800000
      }
    ],
    "objective": "ttp",
    "_doc": "340be685-b1d2-47b3-bcdd-8fa57de61368"
  },
  {
    "data": [
      {
        "symbol": "BTCUSDT_240628",
        "longAccount": "0.5666",
        "longShortRatio": "1.3073",
        "shortAccount": "0.4334",
        "timestamp": 1717966800000
      }
    ],
    "objective": "tta",
    "_doc": "b0963646-e0e5-4d9a-b390-b1ad4ca0ab76"
  },
  {
    "data": [
      {
        "symbol": "BTCUSDC",
        "longAccount": "0.5538",
        "longShortRatio": "1.2411",
        "shortAccount": "0.4462",
        "timestamp": 1717967100000
      }
    ],
    "objective": "gta",
    "_doc": "5e0d1911-2b37-495e-aa7b-b7463863a66c"
  },
  {
    "data": [
      {
        "symbol": "BTCUSDT_240927",
        "longAccount": "0.5397",
        "longShortRatio": "1.1725",
        "shortAccount": "0.4603",
        "timestamp": 1717967100000
      }
    ],
    "objective": "gta",
    "_doc": "d781d659-9399-42b3-bd2e-f7ccce90fc14"
  },
  {
    "data": [
      {
        "symbol": "BTCUSDC",
        "longAccount": "0.5567",
        "longShortRatio": "1.2558",
        "shortAccount": "0.4433",
        "timestamp": 1717966800000
      }
    ],
    "objective": "tta",
    "_doc": "ca46944b-cc82-4579-b53e-f2c39c39a569"
  },
  {
    "data": [
      {
        "longAccount": "0.7377",
        "longShortRatio": "2.8124",
        "shortAccount": "0.2623",
        "pair": "BTCUSD",
        "timestamp": 1717966800000
      }
    ],
    "objective": "tta",
    "_doc": "5599e403-7753-4110-b5d3-c6ad61bc019d"
  },
  {
    "data": [
      {
        "symbol": "BTCDOMUSDT",
        "longAccount": "0.5918",
        "longShortRatio": "1.4498",
        "shortAccount": "0.4082",
        "timestamp": 1717967100000
      }
    ],
    "objective": "gta",
    "_doc": "40395a6d-52df-4f7a-be0f-714c69ed52bc"
  },
  {
    "data": [],
    "objective": "tta",
    "_doc": "16938c3e-42aa-45f2-b9c6-9fcad202d39c"
  },
  {
    "data": [
      {
        "symbol": "BTCDOMUSDT",
        "longAccount": "0.5928",
        "longShortRatio": "1.4558",
        "shortAccount": "0.4072",
        "timestamp": 1717966800000
      }
    ],
    "objective": "tta",
    "_doc": "88e6c9a6-6401-4270-bc92-9e7eedaae178"
  }
]